<?xml version="1.0" encoding="UTF-8"?>
<con:soapui-project id="ae6890c3-f794-4291-b452-a847b103a8ef" created="3.53.0" activeEnvironment="Default environment" encryptionMode="Not encrypted" name="PetStore" projectVersion="" resourceRoot="" updated="3.53.0 2024-05-13T12:06:25Z" xmlns:con="http://eviware.com/soapui/config">
  <con:settings/>
  <con:interface xsi:type="con:RestService" id="d7b5e79d-6ad9-41cc-a56a-516f92e8ef79" wadlVersion="http://wadl.dev.java.net/2009/02" name="https://petstore.swagger.io" type="rest" xmlns:xsi="http://www.w3.org/2001/XMLSchema-instance">
    <con:settings id="efdfc711-46f0-4092-ae22-e0ded049b4b2"/>
    <con:definitionCache type="TEXT" rootPart=""/>
    <con:endpoints>
      <con:endpoint>https://petstore.swagger.io</con:endpoint>
    </con:endpoints>
    <con:resource name="Pet" path="/v2/pet" id="1f03709f-41fb-4cfa-bac9-ee2c6e2991a5">
      <con:settings/>
      <con:parameters/>
      <con:method name="Pet" id="93bbf855-e5b6-4286-9522-c34b8e9ce31b" method="POST">
        <con:settings/>
        <con:parameters/>
        <con:representation type="RESPONSE">
          <con:mediaType>application/json</con:mediaType>
          <con:status>200</con:status>
          <con:params/>
          <con:element xmlns:pet="https://petstore.swagger.io/v2/pet">pet:Response</con:element>
        </con:representation>
        <con:representation type="REQUEST">
          <con:mediaType>application/json</con:mediaType>
          <con:params/>
        </con:representation>
        <con:request name="Request 1" id="e601a5e1-7d62-45f6-8e82-47d515c75fd0" mediaType="application/json">
          <con:settings/>
          <con:endpoint>https://petstore.swagger.io</con:endpoint>
          <con:credentials>
            <con:selectedAuthProfile>No Authorization</con:selectedAuthProfile>
            <con:authType>No Authorization</con:authType>
          </con:credentials>
          <con:parameters/>
        </con:request>
      </con:method>
    </con:resource>
    <con:resource name="FindByStatus" path="/v2/pet/findByStatus" id="562c1d24-6bc6-4ba4-a1eb-9b420b5c8231">
      <con:settings/>
      <con:parameters/>
      <con:method name="FindByStatus" id="b6a70737-a5b7-40cd-9881-59158f56517d" method="GET">
        <con:settings/>
        <con:parameters>
          <con:parameter required="true">
            <con:name>status</con:name>
            <con:value>sold</con:value>
            <con:style>QUERY</con:style>
            <con:default>sold</con:default>
            <con:path xsi:nil="true"/>
            <con:description xsi:nil="true"/>
          </con:parameter>
        </con:parameters>
        <con:representation type="RESPONSE">
          <con:mediaType>application/json</con:mediaType>
          <con:status>200</con:status>
          <con:params/>
          <con:element>Response</con:element>
        </con:representation>
        <con:request name="Request 1" id="423a3b77-4e5f-48c9-bff2-5977c61811f5" mediaType="application/json">
          <con:settings/>
          <con:endpoint>https://petstore.swagger.io</con:endpoint>
          <con:credentials>
            <con:selectedAuthProfile>No Authorization</con:selectedAuthProfile>
            <con:authType>No Authorization</con:authType>
          </con:credentials>
          <con:parameters>
            <con:entry key="status" value="sold"/>
          </con:parameters>
          <con:parameterOrder>
            <con:entry>status</con:entry>
          </con:parameterOrder>
        </con:request>
      </con:method>
    </con:resource>
    <con:resource name="PetId" path="/v2/pet/{petId}" id="de760b13-cfc2-4b32-8358-b27421b7ef93">
      <con:settings/>
      <con:parameters/>
      <con:method name="PetId" id="9f03b368-6706-45cc-8260-1f277c5b548b" method="DELETE">
        <con:settings/>
        <con:parameters>
          <con:parameter required="true">
            <con:name>petId</con:name>
            <con:value>petId</con:value>
            <con:style>TEMPLATE</con:style>
            <con:default>petId</con:default>
            <con:path xsi:nil="true"/>
            <con:description xsi:nil="true"/>
          </con:parameter>
        </con:parameters>
        <con:representation type="REQUEST">
          <con:mediaType>application/json</con:mediaType>
          <con:params/>
        </con:representation>
        <con:representation type="FAULT">
          <con:mediaType>application/json</con:mediaType>
          <con:status>404</con:status>
          <con:params/>
          <con:element xmlns:pet="https://petstore.swagger.io/v2/pet/petId">pet:Fault</con:element>
        </con:representation>
        <con:representation type="RESPONSE">
          <con:mediaType>application/json</con:mediaType>
          <con:status>200</con:status>
          <con:params/>
          <con:element xmlns:pet="https://petstore.swagger.io/v2/pet/petId">pet:Response</con:element>
        </con:representation>
        <con:representation type="FAULT">
          <con:mediaType xsi:nil="true"/>
          <con:status>404</con:status>
          <con:params/>
          <con:element>data</con:element>
        </con:representation>
        <con:request name="Request 1" id="509e5962-90a4-41c3-b6e9-d67f1f9c6e80" mediaType="application/json" postQueryString="false">
          <con:settings/>
          <con:endpoint>https://petstore.swagger.io</con:endpoint>
          <con:request/>
          <con:credentials>
            <con:selectedAuthProfile>No Authorization</con:selectedAuthProfile>
            <con:authType>No Authorization</con:authType>
          </con:credentials>
          <con:jmsConfig JMSDeliveryMode="PERSISTENT"/>
          <con:parameters>
            <con:entry key="petId" value="petId"/>
          </con:parameters>
          <con:parameterOrder>
            <con:entry>petId</con:entry>
          </con:parameterOrder>
        </con:request>
      </con:method>
    </con:resource>
  </con:interface>
  <con:testSuite id="deda10ef-4b1c-4222-a43c-e2ee6d58cf72" name="https://petstore.swagger.io Test Suite">
    <con:settings id="4c028b2e-7203-414f-b9ef-b496c75d1db1"/>
    <con:runType>SEQUENTIAL</con:runType>
    <con:testCase id="13f1ca80-e02e-42d9-a7b2-245870b575e0" discardOkResults="false" failOnError="false" failTestCaseOnErrors="true" keepSession="false" name="Test Case" searchProperties="true" timeout="0">
      <con:settings>
        <con:setting id="IncludeOverview">true</con:setting>
        <con:setting id="IncludeResults">true</con:setting>
        <con:setting id="FlowLayout">false</con:setting>
        <con:setting id="ErrorDetails">true</con:setting>
        <con:setting id="IncludeCoverage">true</con:setting>
      </con:settings>
      <con:testStep type="datasource" name="DataSource" id="8919ef72-96d1-4651-9fa2-e71bdfa4cb7d">
        <con:settings/>
        <con:config xsi:type="con:DataSourceStep" xmlns:xsi="http://www.w3.org/2001/XMLSchema-instance">
          <con:dataSource type="Data Generator">
            <con:configuration>
              <generatedDataCount>10</generatedDataCount>
              <generatorsTotalNumber>3</generatorsTotalNumber>
              <lastSelectedProperty>2</lastSelectedProperty>
              <GeneratorType0>INT</GeneratorType0>
              <PropertyName0>id</PropertyName0>
              <repetitionCountid>0</repetitionCountid>
              <repeatValuesid>false</repeatValuesid>
              <IntegerDataGeneratorMinValueid>74000</IntegerDataGeneratorMinValueid>
              <IntegerDataGeneratorMaxValueid>75000</IntegerDataGeneratorMaxValueid>
              <IntegerDataGeneratorStepValueid>0</IntegerDataGeneratorStepValueid>
              <IntegerDataGeneratorConsequentValuesid>false</IntegerDataGeneratorConsequentValuesid>
              <GeneratorType1>NAME</GeneratorType1>
              <PropertyName1>name</PropertyName1>
              <repetitionCountname>0</repetitionCountname>
              <repeatValuesname>false</repeatValuesname>
              <NameTypeName1>FirstName</NameTypeName1>
              <NameGenderName1>Any</NameGenderName1>
              <GeneratorType2>CUSTOM</GeneratorType2>
              <PropertyName2>status</PropertyName2>
              <repetitionCountstatus>0</repetitionCountstatus>
              <repeatValuesstatus>false</repeatValuesstatus>
              <CustomStringDataGeneratorFormatstatus>alive</CustomStringDataGeneratorFormatstatus>
              <escapeSpaceSequence/>
            </con:configuration>
          </con:dataSource>
          <con:shared>true</con:shared>
          <con:restartShared>true</con:restartShared>
          <con:property>id</con:property>
          <con:property>name</con:property>
          <con:property>status</con:property>
          <con:restartOnRun>true</con:restartOnRun>
          <con:stopDatasourceExhausted>false</con:stopDatasourceExhausted>
        </con:config>
      </con:testStep>
      <con:testStep type="restrequest" name="Post Req" id="77e8295f-7db7-4b37-b05c-b2fc458c250d">
        <con:settings/>
        <con:config service="https://petstore.swagger.io" resourcePath="/v2/pet" methodName="Pet" xsi:type="con:RestRequestStep" xmlns:xsi="http://www.w3.org/2001/XMLSchema-instance">
          <con:restRequest name="Post Req" id="e601a5e1-7d62-45f6-8e82-47d515c75fd0" mediaType="application/json" postQueryString="false">
            <con:settings>
              <con:setting id="com.eviware.soapui.impl.wsdl.WsdlRequest@request-headers">&lt;xml-fragment/></con:setting>
            </con:settings>
            <con:endpoint>https://petstore.swagger.io</con:endpoint>
            <con:request>{\r
   "id" : 772001,\r
   "name" : "Tommyy",\r
   "status" : "alive"\r
}</con:request>
            <con:originalUri>https://petstore.swagger.io/v2/pet</con:originalUri>
            <con:assertion type="Valid HTTP Status Codes" id="b10a34a4-cf9f-47d5-bbb0-316c0b687c41" name="Valid HTTP Status Codes">
              <con:settings/>
              <con:configuration>
                <codes>200</codes>
              </con:configuration>
            </con:assertion>
            <con:credentials>
              <con:selectedAuthProfile>No Authorization</con:selectedAuthProfile>
              <con:authType>No Authorization</con:authType>
            </con:credentials>
            <con:jmsConfig JMSDeliveryMode="PERSISTENT"/>
            <con:parameters/>
          </con:restRequest>
        </con:config>
      </con:testStep>
      <con:testStep type="transfer" name="Property Transfer" id="13c271cd-3551-4a7c-82f7-78359933a784">
        <con:settings/>
        <con:config xsi:type="con:PropertyTransfersStep" xmlns:xsi="http://www.w3.org/2001/XMLSchema-instance">
          <con:transfers setNullOnMissingSource="true" transferTextContent="true" failOnError="true" ignoreEmpty="false" transferToAll="false" entitize="false" transferChildNodes="false">
            <con:name>idTransfer</con:name>
            <con:sourceType>Response</con:sourceType>
            <con:sourceStep>Post Req</con:sourceStep>
            <con:sourcePath>$['id']</con:sourcePath>
            <con:targetType>petId</con:targetType>
            <con:targetStep>Delete Req</con:targetStep>
            <con:targetPath/>
            <con:type>JSONPATH</con:type>
            <con:upgraded>true</con:upgraded>
          </con:transfers>
          <con:transfers setNullOnMissingSource="true" transferTextContent="true" failOnError="true" ignoreEmpty="false" transferToAll="false" entitize="false" transferChildNodes="false">
            <con:name>statusTransfer</con:name>
            <con:sourceType>Response</con:sourceType>
            <con:sourceStep>Post Req</con:sourceStep>
            <con:sourcePath>$['status']</con:sourcePath>
            <con:targetType>status</con:targetType>
            <con:targetStep>Get Req-Activity2</con:targetStep>
            <con:type>JSONPATH</con:type>
            <con:upgraded>true</con:upgraded>
          </con:transfers>
        </con:config>
      </con:testStep>
      <con:testStep type="restrequest" name="Get Req-Activity2" id="3a16f589-76bd-4b0c-9162-c4babbd38407">
        <con:settings/>
        <con:config service="https://petstore.swagger.io" resourcePath="/v2/pet/findByStatus" methodName="FindByStatus" xsi:type="con:RestRequestStep" xmlns:xsi="http://www.w3.org/2001/XMLSchema-instance">
          <con:restRequest name="Get Req-Activity2" id="423a3b77-4e5f-48c9-bff2-5977c61811f5" mediaType="application/json">
            <con:settings>
              <con:setting id="com.eviware.soapui.impl.wsdl.WsdlRequest@request-headers">&lt;xml-fragment/></con:setting>
            </con:settings>
            <con:endpoint>https://petstore.swagger.io</con:endpoint>
            <con:request/>
            <con:originalUri>https://petstore.swagger.io/v2/pet/findByStatus</con:originalUri>
            <con:assertion type="Valid HTTP Status Codes" id="f9938c33-cd30-46ef-916a-048e5f2aeb7d" name="Valid HTTP Status Codes">
              <con:settings/>
              <con:configuration>
                <codes>200</codes>
              </con:configuration>
            </con:assertion>
            <con:credentials>
              <con:selectedAuthProfile>No Authorization</con:selectedAuthProfile>
              <con:authType>No Authorization</con:authType>
            </con:credentials>
            <con:jmsConfig JMSDeliveryMode="PERSISTENT"/>
            <con:parameters/>
            <con:parameterOrder>
              <con:entry>status</con:entry>
            </con:parameterOrder>
          </con:restRequest>
        </con:config>
      </con:testStep>
      <con:testStep type="restrequest" name="Delete Req" id="24023d37-d52f-4be3-a451-3ef02ed6641a">
        <con:settings/>
        <con:config service="https://petstore.swagger.io" resourcePath="/v2/pet/{petId}" methodName="PetId" xsi:type="con:RestRequestStep" xmlns:xsi="http://www.w3.org/2001/XMLSchema-instance">
          <con:restRequest name="Delete Req" id="509e5962-90a4-41c3-b6e9-d67f1f9c6e80" mediaType="application/json" postQueryString="false">
            <con:settings>
              <con:setting id="com.eviware.soapui.impl.wsdl.WsdlRequest@request-headers">&lt;xml-fragment/></con:setting>
            </con:settings>
            <con:endpoint>https://petstore.swagger.io</con:endpoint>
            <con:request/>
            <con:originalUri>https://petstore.swagger.io/v2/pet/petId</con:originalUri>
            <con:assertion type="Valid HTTP Status Codes" id="7968434b-12cd-49a5-8ca3-c21fbd7d0219" name="Valid HTTP Status Codes">
              <con:settings/>
              <con:configuration>
                <codes>200</codes>
              </con:configuration>
            </con:assertion>
            <con:credentials>
              <con:selectedAuthProfile>No Authorization</con:selectedAuthProfile>
              <con:authType>No Authorization</con:authType>
            </con:credentials>
            <con:jmsConfig JMSDeliveryMode="PERSISTENT"/>
            <con:parameters>
              <con:entry key="petId" value="772001"/>
            </con:parameters>
            <con:parameterOrder>
              <con:entry>petId</con:entry>
            </con:parameterOrder>
          </con:restRequest>
        </con:config>
      </con:testStep>
      <con:testStep type="datasourceloop" name="Data Source Loop" id="ccf987b3-56f9-4244-94f1-41e75c9265bb">
        <con:settings/>
        <con:config>
          <dataSourceStep>DataSource</dataSourceStep>
          <targetStep>Post Req</targetStep>
          <discardResults>true</discardResults>
        </con:config>
      </con:testStep>
      <con:properties/>
      <con:reportParameters/>
      <con:breakPoints>
        <con:testStepId>8919ef72-96d1-4651-9fa2-e71bdfa4cb7d</con:testStepId>
        <con:status>NONE</con:status>
        <con:properties/>
      </con:breakPoints>
      <con:breakPoints>
        <con:testStepId>77e8295f-7db7-4b37-b05c-b2fc458c250d</con:testStepId>
        <con:status>NONE</con:status>
        <con:properties/>
      </con:breakPoints>
      <con:breakPoints>
        <con:testStepId>13c271cd-3551-4a7c-82f7-78359933a784</con:testStepId>
        <con:status>NONE</con:status>
        <con:properties/>
      </con:breakPoints>
      <con:breakPoints>
        <con:testStepId>3a16f589-76bd-4b0c-9162-c4babbd38407</con:testStepId>
        <con:status>NONE</con:status>
        <con:properties/>
      </con:breakPoints>
      <con:breakPoints>
        <con:testStepId>24023d37-d52f-4be3-a451-3ef02ed6641a</con:testStepId>
        <con:status>NONE</con:status>
        <con:properties/>
      </con:breakPoints>
      <con:breakPoints>
        <con:testStepId>ccf987b3-56f9-4244-94f1-41e75c9265bb</con:testStepId>
        <con:status>NONE</con:status>
        <con:properties/>
      </con:breakPoints>
    </con:testCase>
    <con:properties/>
    <con:reportParameters/>
  </con:testSuite>
  <con:requirements/>
  <con:properties/>
  <con:wssContainer/>
  <con:databaseConnectionContainer/>
  <con:jmsConnectionContainer/>
  <con:oAuth2ProfileContainer/>
  <con:oAuth1ProfileContainer/>
  <con:reporting>
    <con:xmlTemplates/>
    <con:parameters/>
  </con:reporting>
  <con:eventHandlers type="RequestFilter.filterRequest" name="RequestFilter.filterRequest">
    <con:script>// Sample event script to add custom HTTP header to all outgoing REST, SOAP and HTTP(S) calls
// This code is often used for adding custom authentication to ReadyAPI functional tests

// If hardcoding the token, uncomment and change line 5
// token = '4567'

// If your token is parameterized in Project level custom property, uncomment line 8
// token = request.parent.testCase.testSuite.project.getProperty('auth_token').getValue()

// To modify all outgoing calls, remove comments from lines 11 to 16
// headers = request.requestHeaders
// if (headers.containsKey('auth_token2') == false) {
//   headers.put('auth_token2', token)
//   request.requestHeaders = headers
// }</con:script>
  </con:eventHandlers>
  <con:eventHandlers type="TestRunListener.afterStep" name="TestRunListener.afterStep">
    <con:script>// Save all test step results into files
// Change the directory path in line 5 to a location where you want to store details
// then uncomment lines 5 to 10

// filePath = 'C:\\tempOutputDirectory\\'
// fos = new java.io.FileOutputStream(filePath + testStepResult.testStep.label + '.txt', true)
// pw = new java.io.PrintWriter(fos)
// testStepResult.writeTo(pw)
// pw.close()
// fos.close()</con:script>
  </con:eventHandlers>
  <con:authRepository/>
  <con:tags/>
</con:soapui-project>
